pydbcx_mcp/__init__.py
pydbcx_mcp/server.py
mseep_pydbcx_mcp-0.1.7.dist-info/METADATA
mseep_pydbcx_mcp-0.1.7.dist-info/WHEEL
mseep_pydbcx_mcp-0.1.7.dist-info/entry_points.txt
mseep_pydbcx_mcp-0.1.7.dist-info/licenses/LICENSE
mseep_pydbcx_mcp-0.1.7.dist-info/RECORD
