Metadata-Version: 2.4
Name: mseep-pydbcx-mcp
Version: 0.1.7
Summary: JDBCX MCP Server
Project-URL: Homepage, https://github.com/jdbcx/pydbcx-mcp
Project-URL: Documentation, https://github.com/jdbcx/pydbcx-mcp/blob/main/README.md
Project-URL: Repository, https://github.com/jdbcx/pydbcx-mcp.git
Project-URL: Bug Tracker, https://github.com/jdbcx/pydbcx-mcp/issues
Author-email: mseep <support@skydeck.ai>
License: Apache License (2.0)
License-File: LICENSE
Keywords: automation,database,jdbc,llm,mcp
Classifier: Development Status :: 4 - Beta
Classifier: Intended Audience :: Developers
Classifier: Intended Audience :: System Administrators
Classifier: License :: OSI Approved :: Apache Software License
Classifier: Programming Language :: Python :: 3
Classifier: Programming Language :: Python :: 3.10
Requires-Python: >=3.10
Requires-Dist: httpx>=0.28.1
Requires-Dist: mcp[cli]>=1.6.0
